takelessons_scraper/__init__.py
takelessons_scraper/__version__
takelessons_scraper/selenium_tools.py
takelessons_scraper/takelessons_scraper.py
takelessons_scraper-0.0.3.dist-info/LICENSE
takelessons_scraper-0.0.3.dist-info/METADATA
takelessons_scraper-0.0.3.dist-info/WHEEL
takelessons_scraper-0.0.3.dist-info/top_level.txt
takelessons_scraper-0.0.3.dist-info/RECORD
