Metadata-Version: 2.1
Name: takelessons-scraper
Version: 0.0.3
Summary: Scrape chat content from TakeLessons.com
Home-page: UNKNOWN
Author: EliMor
Author-email: elimor.github@gmail.com
License: This is free and unencumbered software released into the public domain.        
Platform: UNKNOWN
Classifier: Programming Language :: Python :: 3.6
Classifier: Programming Language :: Python :: 3.7
Classifier: Programming Language :: Python :: 3.8
Classifier: Programming Language :: Python :: 3.9
License-File: LICENSE
Requires-Dist: requests (>=2.25.1)
Requires-Dist: selenium (>=3.141.0)
Requires-Dist: pendulum (>=2.1.2)
Provides-Extra: tests
Requires-Dist: pytest ; extra == 'tests'
